react_django/__init__.py
react_django/__main__.py
react_django/cli.py
react_django-0.1.2.dist-info/licenses/LICENSE
react_django-0.1.2.dist-info/METADATA
react_django-0.1.2.dist-info/WHEEL
react_django-0.1.2.dist-info/entry_points.txt
react_django-0.1.2.dist-info/top_level.txt
react_django-0.1.2.dist-info/RECORD
