Metadata-Version: 2.4
Name: react_django
Version: 0.1.2
Summary: CLI to scaffold fullstack React + Django + Tailwind projects
Home-page: https://github.com/yourusername/automated-fullstack-cli
Author: ISAAC EDZORDZI FIAVOR
Author-email: isaacfiavor0611@gmail.com
Classifier: Programming Language :: Python :: 3
Classifier: License :: OSI Approved :: MIT License
Classifier: Operating System :: OS Independent
Requires-Python: >=3.7
License-File: LICENSE
Dynamic: author
Dynamic: author-email
Dynamic: classifier
Dynamic: description
Dynamic: description-content-type
Dynamic: home-page
Dynamic: license-file
Dynamic: requires-python
Dynamic: summary
